sx_rest_data/__init__.py
sx_rest_data/main.py
sx_rest_data/spss_syntax/__init__.py
sx_rest_data/spss_syntax/generate_dataset.py
sx_rest_data/spss_syntax/generate_labels.py
sx_rest_data/spss_syntax/generate_open_all.py
sx_rest_data/spss_syntax/templates/generate_spss_datafiles.txt
sx_rest_data/spss_syntax/templates/open_single_dataset_in_spss.txt
sx_rest_data/validate_inputs/__init__.py
sx_rest_data/validate_inputs/validate_credentials.py
sx_rest_data/validate_inputs/validate_orgid.py
sx_rest_data/validate_inputs/validate_output_path.py
sx_rest_data/validate_inputs/validate_surveyids.py
sx_rest_data-0.1.7.dist-info/METADATA
sx_rest_data-0.1.7.dist-info/WHEEL
sx_rest_data-0.1.7.dist-info/RECORD
