Metadata-Version: 2.1
Name: sx-rest-data
Version: 0.1.7
Summary: 
Author: Christian Frost
Author-email: ctf@ramboll.com
Requires-Python: >=3.12,<4.0
Classifier: Programming Language :: Python :: 3
Classifier: Programming Language :: Python :: 3.12
Requires-Dist: ipykernel (>=6.29.3,<7.0.0)
Requires-Dist: keyring (>=25.2.1,<26.0.0)
Requires-Dist: loguru (>=0.7.2,<0.8.0)
Requires-Dist: pandas (>=2.2.2,<3.0.0)
Requires-Dist: requests (>=2.31.0,<3.0.0)
